<?xml version="1.0" encoding="utf-8"?>
<!DOCTYPE hibernate-mapping PUBLIC "-//Hibernate/Hibernate Mapping DTD 3.0//EN"
                                   "http://hibernate.sourceforge.net/hibernate-mapping-3.0.dtd">
<!-- 
    Mapping file autogenerated by MyEclipse Persistence Tools
-->
<hibernate-mapping>
 <class name="cc.messcat.entity.Legal" table="legal">
        <id name="id" type="java.lang.Long">
            <column name="ID" />
            <generator class="identity" />
        </id>
        <many-to-one name="regionId" class="cc.messcat.entity.Region" cascade="none" fetch="select" lazy="false">
        	<column name="regionID">
                <comment>地区ID</comment>
            </column>
        </many-to-one>
        <property name="regionName" type="java.lang.String">
            <column name="region_name" length="100">
                <comment>地区名（选填）</comment>
            </column>
        </property>
        <property name="productIds" type="java.lang.String">
            <column name="productIDs" length="500">
                <comment>产品ID</comment>
            </column>
        </property>
        <property name="productNames" type="java.lang.String">
            <column name="product_names" length="1073741823">
                <comment>产品名集（选填）</comment>
            </column>
        </property>
        <property name="item" type="java.lang.String">
            <column name="item" length="100">
                <comment>条目名称</comment>
            </column>
        </property>
        <property name="content" type="java.lang.String">
            <column name="content" length="1073741823">
                <comment>内容</comment>
            </column>
        </property>
        <property name="remark" type="java.lang.String">
            <column name="remark" length="500">
                <comment>备注</comment>
            </column>
        </property>
        <property name="citeId" type="java.lang.Long">
            <column name="citeID">
                <comment>引用ID</comment>
            </column>
        </property>
        <property name="addTime" type="java.util.Date">
            <column name="add_time" length="19">
                <comment>新增时间</comment>
            </column>
        </property>
        <property name="editTime" type="java.util.Date">
            <column name="edit_time" length="19">
                <comment>编辑时间</comment>
            </column>
        </property>
        <property name="status" type="java.lang.String">
            <column name="status" length="1">
                <comment>0：可用 1：禁用</comment>
            </column>
        </property>
    </class>
</hibernate-mapping>
